{
  "total_customers": 4339,
  "segment_distribution": {
    "Lost": 2387,
    "Champions": 839,
    "Loyal Customers": 427,
    "New Customers": 273,
    "Hibernating": 183,
    "Potential Loyalists": 124,
    "At Risk": 60,
    "Cannot Lose Them": 46
  },
  "rfm_score_distribution": {
    "111": 182,
    "112": 127,
    "113": 33,
    "114": 17,
    "115": 4,
    "121": 153,
    "122": 91,
    "123": 43,
    "124": 10,
    "125": 4,
    "131": 21,
    "132": 55,
    "133": 39,
    "134": 21,
    "135": 5,
    "141": 3,
    "142": 10,
    "143": 18,
    "144": 14,
    "145": 3,
    "152": 1,
    "153": 3,
    "154": 3,
    "155": 5,
    "211": 81,
    "212": 61,
    "213": 40,
    "214": 14,
    "215": 3,
    "221": 65,
    "222": 61,
    "223": 50,
    "224": 22,
    "225": 4,
    "231": 25,
    "232": 53,
    "233": 83,
    "234": 52,
    "235": 13,
    "241": 6,
    "242": 15,
    "243": 46,
    "244": 69,
    "245": 29,
    "251": 1,
    "253": 5,
    "254": 17,
    "255": 28,
    "311": 67,
    "312": 58,
    "313": 28,
    "314": 9,
    "315": 2,
    "321": 68,
    "322": 57,
    "323": 35,
    "324": 22,
    "325": 5,
    "331": 19,
    "332": 49,
    "333": 68,
    "334": 37,
    "335": 13,
    "341": 5,
    "342": 11,
    "343": 65,
    "344": 82,
    "345": 40,
    "353": 5,
    "354": 33,
    "355": 80,
    "411": 56,
    "412": 29,
    "413": 13,
    "414": 1,
    "415": 1,
    "421": 39,
    "422": 45,
    "423": 20,
    "424": 13,
    "425": 4,
    "431": 18,
    "432": 50,
    "433": 62,
    "434": 40,
    "435": 8,
    "442": 15,
    "443": 80,
    "444": 119,
    "445": 44,
    "452": 1,
    "453": 7,
    "454": 63,
    "455": 177,
    "511": 20,
    "512": 17,
    "513": 4,
    "515": 1,
    "521": 16,
    "522": 14,
    "523": 16,
    "524": 10,
    "525": 1,
    "531": 20,
    "532": 33,
    "533": 44,
    "534": 33,
    "535": 6,
    "541": 2,
    "542": 14,
    "543": 52,
    "544": 85,
    "545": 41,
    "551": 1,
    "552": 1,
    "553": 8,
    "554": 82,
    "555": 347
  },
  "segment_statistics": {
    "Recency_mean": {
      "At Risk": 211.25,
      "Cannot Lose Them": 101.65,
      "Champions": 11.49,
      "Hibernating": 92.35,
      "Lost": 139.54,
      "Loyal Customers": 36.97,
      "New Customers": 28.54,
      "Potential Loyalists": 7.17
    },
    "Recency_median": {
      "At Risk": 206.0,
      "Cannot Lose Them": 92.5,
      "Champions": 9.0,
      "Hibernating": 74.0,
      "Lost": 107.0,
      "Loyal Customers": 38.0,
      "New Customers": 25.0,
      "Potential Loyalists": 8.0
    },
    "Frequency_mean": {
      "At Risk": 3.08,
      "Cannot Lose Them": 5.37,
      "Champions": 12.11,
      "Hibernating": 1.4,
      "Lost": 2.01,
      "Loyal Customers": 5.27,
      "New Customers": 1.07,
      "Potential Loyalists": 2.76
    },
    "Frequency_median": {
      "At Risk": 1.0,
      "Cannot Lose Them": 5.0,
      "Champions": 8.0,
      "Hibernating": 1.0,
      "Lost": 2.0,
      "Loyal Customers": 4.0,
      "New Customers": 1.0,
      "Potential Loyalists": 2.0
    },
    "Monetary_mean": {
      "At Risk": 3083.05,
      "Cannot Lose Them": 2287.39,
      "Champions": 6705.72,
      "Hibernating": 160.98,
      "Lost": 764.32,
      "Loyal Customers": 2335.2,
      "New Customers": 221.53,
      "Potential Loyalists": 478.96
    },
    "Monetary_median": {
      "At Risk": 1414.38,
      "Cannot Lose Them": 2255.02,
      "Champions": 2993.1,
      "Hibernating": 167.61,
      "Lost": 482.2,
      "Loyal Customers": 1611.59,
      "New Customers": 199.48,
      "Potential Loyalists": 436.89
    },
    "Monetary_sum": {
      "At Risk": 184982.95,
      "Cannot Lose Them": 105220.15,
      "Champions": 5626103.01,
      "Hibernating": 29458.59,
      "Lost": 1824441.78,
      "Loyal Customers": 997131.91,
      "New Customers": 60478.94,
      "Potential Loyalists": 59391.56
    }
  },
  "r_score_distribution": {
    "1": 865,
    "2": 843,
    "3": 858,
    "4": 905,
    "5": 868
  },
  "f_score_distribution": {
    "1": 868,
    "2": 868,
    "3": 867,
    "4": 868,
    "5": 868
  },
  "m_score_distribution": {
    "1": 868,
    "2": 868,
    "3": 867,
    "4": 868,
    "5": 868
  }
}